tap_pulumi_cloud/__init__.py
tap_pulumi_cloud/__main__.py
tap_pulumi_cloud/client.py
tap_pulumi_cloud/streams.py
tap_pulumi_cloud/tap.py
tap_pulumi_cloud-0.3.3.dist-info/LICENSE
tap_pulumi_cloud-0.3.3.dist-info/METADATA
tap_pulumi_cloud-0.3.3.dist-info/WHEEL
tap_pulumi_cloud-0.3.3.dist-info/entry_points.txt
tap_pulumi_cloud-0.3.3.dist-info/RECORD
