Metadata-Version: 2.3
Name: tap-pulumi-cloud
Version: 0.3.3
Summary: Singer tap for Pulumi Cloud, built with the Meltano SDK for Singer Taps.
License: Apache-2.0
Keywords: ELT,singer.io,Pulumi Cloud
Author: Edgar Ramírez-Mondragón
Author-email: edgarrm358@gmail.com
Requires-Python: >=3.10,<4
Classifier: License :: OSI Approved :: Apache Software License
Classifier: Programming Language :: Python :: 3
Classifier: Programming Language :: Python :: 3.10
Classifier: Programming Language :: Python :: 3.11
Classifier: Programming Language :: Python :: 3.12
Classifier: Programming Language :: Python :: 3.13
Classifier: Programming Language :: Python :: 3.14
Requires-Dist: pyhumps (>=3.8.0,<4)
Requires-Dist: requests-cache (>=1.0.1,<2)
Requires-Dist: singer-sdk (>=0.48.1,<0.49.0)
Project-URL: Documentation, https://github.com/edgarrmondragon/tap-pulumi-cloud#readme
Project-URL: Homepage, https://github.com/edgarrmondragon/tap-pulumi-cloud
Project-URL: Repository, https://github.com/edgarrmondragon/tap-pulumi-cloud
